dummy_api/__init__.py
dummy_api/api_template.py
dummy_api/generator.py
dummy_api_package-0.1.dist-info/METADATA
dummy_api_package-0.1.dist-info/WHEEL
dummy_api_package-0.1.dist-info/entry_points.txt
dummy_api_package-0.1.dist-info/top_level.txt
dummy_api_package-0.1.dist-info/RECORD
